zope/app/zcmlfiles/__init__.py
zope/app/zcmlfiles/browser.zcml
zope/app/zcmlfiles/configure.zcml
zope/app/zcmlfiles/ftesting.zcml
zope/app/zcmlfiles/menus.zcml
zope/app/zcmlfiles/meta.zcml
zope/app/zcmlfiles/tests.py
zope_app_zcmlfiles-6.0.dist-info/licenses/LICENSE.txt
zope_app_zcmlfiles-6.0.dist-info/METADATA
zope_app_zcmlfiles-6.0.dist-info/WHEEL
zope_app_zcmlfiles-6.0.dist-info/top_level.txt
zope_app_zcmlfiles-6.0.dist-info/RECORD
