Metadata-Version: 2.4
Name: zope.app.zcmlfiles
Version: 6.0
Summary: Zope application server ZCML files
Home-page: http://github.com/zopefoundation/zope.app.zcmlfiles
Author: Zope Foundation and Contributors
Author-email: zope-dev@zope.dev
License: ZPL-2.1
Keywords: zope setup configuration standard menu
Classifier: Development Status :: 5 - Production/Stable
Classifier: Intended Audience :: Developers
Classifier: License :: OSI Approved :: Zope Public License
Classifier: Programming Language :: Python
Classifier: Programming Language :: Python :: 3
Classifier: Programming Language :: Python :: 3.9
Classifier: Programming Language :: Python :: 3.10
Classifier: Programming Language :: Python :: 3.11
Classifier: Programming Language :: Python :: 3.12
Classifier: Programming Language :: Python :: 3.13
Classifier: Programming Language :: Python :: Implementation :: CPython
Classifier: Programming Language :: Python :: Implementation :: PyPy
Classifier: Operating System :: OS Independent
Classifier: Topic :: Internet :: WWW/HTTP
Classifier: Topic :: Software Development
Classifier: Framework :: Zope :: 3
Requires-Python: >=3.9
License-File: LICENSE.txt
Requires-Dist: setuptools
Requires-Dist: zope.annotation>=4.4.1
Requires-Dist: zope.component>=4.3.0
Requires-Dist: zope.componentvocabulary>=2.0.0
Requires-Dist: zope.copypastemove>=4.0.0
Requires-Dist: zope.dublincore>=4.1.1
Requires-Dist: zope.formlib>=4.3.0
Requires-Dist: zope.i18n>=4.2.0
Requires-Dist: zope.location>=4.0.3
Requires-Dist: zope.publisher>=4.3.2
Requires-Dist: zope.size>=4.1.0
Requires-Dist: zope.traversing>=4.1.0
Requires-Dist: zope.app.applicationcontrol>=4.0.0
Requires-Dist: zope.app.appsetup>=4.0.0
Requires-Dist: zope.app.basicskin>=4.0.0
Requires-Dist: zope.app.broken>=4.0.0
Requires-Dist: zope.app.component>=4.0.0
Requires-Dist: zope.app.container>=4.0.0
Requires-Dist: zope.app.content>=4.0.0
Requires-Dist: zope.app.dependable>=4.0.0
Requires-Dist: zope.app.error>=4.0.0
Requires-Dist: zope.app.exception>=4.0.1
Requires-Dist: zope.app.folder>=4.0.0
Requires-Dist: zope.app.form>=5.0.0
Requires-Dist: zope.app.generations>=4.0.0
Requires-Dist: zope.app.http>=4.0.1
Requires-Dist: zope.app.i18n>=4.0.0
Requires-Dist: zope.app.locales>=4.0.0
Requires-Dist: zope.app.pagetemplate>=4.0.0
Requires-Dist: zope.app.principalannotation>=4.0.0
Requires-Dist: zope.app.publication>=4.2.1
Requires-Dist: zope.app.publisher>=4.0.0
Requires-Dist: zope.app.rotterdam>=4.0.0
Requires-Dist: zope.app.schema>=4.1.0
Requires-Dist: zope.app.security>=4.0.0
Requires-Dist: zope.app.wsgi>=4.1.0
Provides-Extra: test
Requires-Dist: webtest; extra == "test"
Requires-Dist: zope.testing; extra == "test"
Requires-Dist: zope.testrunner>=6.4; extra == "test"
Dynamic: author
Dynamic: author-email
Dynamic: classifier
Dynamic: description
Dynamic: home-page
Dynamic: keywords
Dynamic: license
Dynamic: license-file
Dynamic: provides-extra
Dynamic: requires-dist
Dynamic: requires-python
Dynamic: summary
